src/__init__.py
src/__main__.py
src/yaml_docs_parser.py
src/extensions/__init__.py
src/extensions/jinja_filters.py
src/extensions/jinja_functions.py
src/extensions/jinja_tests.py
src/factories/__init__.py
src/factories/jinja_template_factory.py
src/factory/__init__.py
src/factory/jinja_template_factory.py
src/helpers/__init__.py
src/helpers/file_helper.py
src/helpers/string_helper.py
src/helpers/yaml_comment_helper.py
src/models/__init__.py
src/models/file_details.py
src/wrappers/__init__.py
src/wrappers/jinja_environment_wrapper.py
src/wrappers/jinja_template_wrapper.py
src/wrappers/ruamel_yaml_wrapper.py
tests/__init__.py
tests/functional/__init__.py
tests/unit/__init__.py
embedded_yaml_docs-0.0.12.dist-info/LICENSE
embedded_yaml_docs-0.0.12.dist-info/METADATA
embedded_yaml_docs-0.0.12.dist-info/WHEEL
embedded_yaml_docs-0.0.12.dist-info/entry_points.txt
embedded_yaml_docs-0.0.12.dist-info/top_level.txt
embedded_yaml_docs-0.0.12.dist-info/RECORD
