Metadata-Version: 2.1
Name: embedded-yaml-docs
Version: 0.0.12
Summary: embedded_yaml_docs is a CLI used for generating markdown documentation, from your YAML files. This can be useful for documenting YAML files such as CI pipelines.
Home-page: https://github.com/GenesisCoast/embedded-yaml-docs
Author: Harry Sanderson
Author-email: harrysanderson@hotmail.co.uk
License: MIT
Platform: UNKNOWN
Classifier: Development Status :: 4 - Beta
Classifier: Intended Audience :: Developers
Classifier: License :: OSI Approved :: MIT License
Classifier: Natural Language :: English
Classifier: Programming Language :: Python :: 3
Classifier: Programming Language :: Python :: 3.5
Classifier: Programming Language :: Python :: 3.6
Classifier: Programming Language :: Python :: 3.7
Classifier: Programming Language :: Python :: Implementation :: CPython
Requires-Dist: click
Requires-Dist: Jinja2
Requires-Dist: pyfiglet
Requires-Dist: ruamel.yaml
Requires-Dist: markupsafe
